django_sweetcaptcha-0.1.dist-info/DESCRIPTION.rst
django_sweetcaptcha-0.1.dist-info/METADATA
django_sweetcaptcha-0.1.dist-info/metadata.json
django_sweetcaptcha-0.1.dist-info/RECORD
django_sweetcaptcha-0.1.dist-info/top_level.txt
django_sweetcaptcha-0.1.dist-info/WHEEL
sweetcaptcha/__init__.py
sweetcaptcha/client.py
sweetcaptcha/fields.py
sweetcaptcha/widgets.py
