Metadata-Version: 2.0
Name: django-sweetcaptcha
Version: 0.1
Summary: A simple Django sweetcaptcha field/form app.
Home-page: http://github.com/jordij/django-sweetcaptcha
Author: Jordi J. Tablada
Author-email: hi@jordijoan.me
License: BSD License
Platform: UNKNOWN
Classifier: Environment :: Web Environment
Classifier: Framework :: Django
Classifier: Intended Audience :: Developers
Classifier: License :: OSI Approved :: BSD License
Classifier: Operating System :: OS Independent
Classifier: Programming Language :: Python
Classifier: Topic :: Internet :: WWW/HTTP
Classifier: Topic :: Internet :: WWW/HTTP :: Dynamic Content
